{"title":"2022.9.8 做题记录","uid":"adb1df164dad34d1bec9db2b070e6769","slug":"2022-9-8-做题记录","date":"2022-09-08T03:36:25.000Z","updated":"2022-09-15T12:10:06.896Z","comments":true,"path":"api/articles/2022-9-8-做题记录.json","keywords":null,"cover":null,"content":"\n","feature":false,"text":" ","link":"","photos":[],"count_time":{"symbolsCount":1,"symbolsTime":"1 mins."},"categories":[{"name":"做题记录","slug":"做题记录","count":16,"path":"api/categories/做题记录.json"}],"tags":[{"name":"DP","slug":"DP","count":10,"path":"api/tags/DP.json"}],"toc":"","author":{"name":"HYLTianMeng","slug":"blog-author","avatar":"https://pic.imgdb.cn/item/6291f9de0947543129a4c41f.jpg","link":"/","description":"一只蒟蒻 OIer，坐标 SD。","socials":{"github":"https://github.com/hylTianMeng","twitter":"","stackoverflow":"","wechat":"","qq":"","weibo":"","zhihu":"https://www.zhihu.com/people/tian-meng-10-29","csdn":"https://blog.csdn.net/hh1215962534?spm=1000.2115.3001.5343","juejin":"","customs":{}}},"mapped":true,"prev_post":{"title":"我们仍未知道那些题的解法","uid":"144ade7b936ec62a125538cf88cfe7c5","slug":"我们仍未知道那些题的解法","date":"2022-09-12T08:54:15.000Z","updated":"2022-09-12T10:26:17.127Z","comments":true,"path":"api/articles/我们仍未知道那些题的解法.json","keywords":null,"cover":"https://pic.imgdb.cn/item/631f094d16f2c2beb1652d45.jpg","text":"这里放亿些我仍然没有切掉的思维难度或代码难度很大的题目。 ZR 泡泡糖 【PR #6】情报传递 2 ","link":"","photos":[],"count_time":{"symbolsCount":52,"symbolsTime":"1 mins."},"categories":[{"name":"做题记录","slug":"做题记录","count":16,"path":"api/categories/做题记录.json"}],"tags":[],"author":{"name":"HYLTianMeng","slug":"blog-author","avatar":"https://pic.imgdb.cn/item/6291f9de0947543129a4c41f.jpg","link":"/","description":"一只蒟蒻 OIer，坐标 SD。","socials":{"github":"https://github.com/hylTianMeng","twitter":"","stackoverflow":"","wechat":"","qq":"","weibo":"","zhihu":"https://www.zhihu.com/people/tian-meng-10-29","csdn":"https://blog.csdn.net/hh1215962534?spm=1000.2115.3001.5343","juejin":"","customs":{}}},"feature":false},"next_post":{"title":"狄利克雷卷积前缀和","uid":"e76e5f37ac74019cc4e883006ae7a5c7","slug":"狄利克雷卷积前缀和","date":"2022-09-08T02:16:23.000Z","updated":"2022-09-08T03:08:49.567Z","comments":true,"path":"api/articles/狄利克雷卷积前缀和.json","keywords":null,"cover":"https://pic.imgdb.cn/item/63195ceb16f2c2beb1d23f4d.jpg","text":"给定积性函数 ，且已经得到 所有 处的前缀和 ，现在要求 所有 处的前缀和。 简单推导后可得： 可以整数分块，对于所有的 来说，如果直接做的话，复杂度是： 实际上，我们可以利用杜教筛一样的预处理，对于所有 以内的 ，全都预处理。这样的复杂度应该为： 由于 是积性函数，所以可以利用...","link":"","photos":[],"count_time":{"symbolsCount":175,"symbolsTime":"1 mins."},"categories":[{"name":"Math","slug":"Math","count":23,"path":"api/categories/Math.json"}],"tags":[{"name":"数论","slug":"数论","count":8,"path":"api/tags/数论.json"}],"author":{"name":"HYLTianMeng","slug":"blog-author","avatar":"https://pic.imgdb.cn/item/6291f9de0947543129a4c41f.jpg","link":"/","description":"一只蒟蒻 OIer，坐标 SD。","socials":{"github":"https://github.com/hylTianMeng","twitter":"","stackoverflow":"","wechat":"","qq":"","weibo":"","zhihu":"https://www.zhihu.com/people/tian-meng-10-29","csdn":"https://blog.csdn.net/hh1215962534?spm=1000.2115.3001.5343","juejin":"","customs":{}}},"feature":false}}