{"name":"EXKMP","slug":"EXKMP","count":1,"postlist":[{"title":"KMP与EXKMP","uid":"eae4a0a212e1c499849f3db3fd2bd0f6","slug":"KMP与EXKMP","date":"2022-08-02T08:22:09.000Z","updated":"2022-08-02T13:07:42.689Z","comments":true,"path":"api/articles/KMP与EXKMP.json","keywords":null,"cover":"https://pic.imgdb.cn/item/62e8e1c816f2c2beb1e8dfab.jpg","text":"KMP 算法 问题引入 KMP 算法可以解决这样一类问题：给定一个字符串 ，我们称为主串，给定字符串 ，我们称之为模式串。我们需要用模式串去匹配主串，也就是说，看看模式串有没有在主串中出现过，如果出现过那么在哪里出现？出现过几次。 不难想到，暴力是可以做的，时间复杂度为 ，我们只...","link":"","photos":[],"count_time":{"symbolsCount":"2.1k","symbolsTime":"2 mins."},"categories":[{"name":"算法","slug":"算法","count":4,"path":"api/categories/算法.json"}],"tags":[{"name":"KMP","slug":"KMP","count":1,"path":"api/tags/KMP.json"},{"name":"EXKMP","slug":"EXKMP","count":1,"path":"api/tags/EXKMP.json"}],"author":{"name":"HYLTianMeng","slug":"blog-author","avatar":"https://pic.imgdb.cn/item/6291f9de0947543129a4c41f.jpg","link":"/","description":"一只蒟蒻 OIer，坐标 SD。","socials":{"github":"https://github.com/hylTianMeng","twitter":"","stackoverflow":"","wechat":"","qq":"","weibo":"","zhihu":"https://www.zhihu.com/people/tian-meng-10-29","csdn":"https://blog.csdn.net/hh1215962534?spm=1000.2115.3001.5343","juejin":"","customs":{}}},"feature":false}]}